clonal_expansion_modeling_tools/__init__.py
clonal_expansion_modeling_tools/gesus_routines.py
clonal_expansion_modeling_tools/moran_models.py
clonal_expansion_modeling_tools-0.0.1.dist-info/licenses/LICENSE
clonal_expansion_modeling_tools-0.0.1.dist-info/WHEEL
clonal_expansion_modeling_tools-0.0.1.dist-info/METADATA
clonal_expansion_modeling_tools-0.0.1.dist-info/RECORD
